send_gmail/__init__.py
send_gmail-0.0.3.dist-info/LICENSE
send_gmail-0.0.3.dist-info/METADATA
send_gmail-0.0.3.dist-info/WHEEL
send_gmail-0.0.3.dist-info/top_level.txt
send_gmail-0.0.3.dist-info/RECORD
