Metadata-Version: 2.1
Name: send-gmail
Version: 0.0.3
Summary: Send smtp mail
Author-email: Detlef Meyer <detlefm@dmone.de>
License: MIT License
Project-URL: Homepage, https://github.com/detlefm/send_gmail
Project-URL: Bug Tracker, https://github.com/detlefm/send_gmail/issues
Classifier: Programming Language :: Python :: 3
Classifier: License :: OSI Approved :: MIT License
Classifier: Operating System :: OS Independent
Requires-Python: >=3.8
License-File: LICENSE
